Metadata-Version: 1.0
Name: probdist-metrics
Version: 0.1
Summary: Gaussian and Binomial distribution metrics
Home-page: UNKNOWN
Author: Vikash Sharma
Author-email: vikash.sharma.inbox@gmail.com
License: UNKNOWN
Platform: UNKNOWN
